pyTelegramBotCAPTCHA/__init__.py
pyTelegramBotCAPTCHA/telebot_captcha.py
pyTelegramBotCAPTCHA/data/languages.json
pyTelegramBotCAPTCHA/data/fonts/Cute_Font.ttf
pyTelegramBotCAPTCHA/data/fonts/Love.ttf
pyTelegramBotCAPTCHA/data/fonts/My_Unprofessional_Handwriting.ttf
pyTelegramBotCAPTCHA/data/fonts/PlainAndSimple-Regular.ttf
pyTelegramBotCAPTCHA/data/fonts/WinterLandByJd-Bold.ttf
pyTelegramBotCAPTCHA-1.1.4.dist-info/LICENSE
pyTelegramBotCAPTCHA-1.1.4.dist-info/METADATA
pyTelegramBotCAPTCHA-1.1.4.dist-info/WHEEL
pyTelegramBotCAPTCHA-1.1.4.dist-info/top_level.txt
pyTelegramBotCAPTCHA-1.1.4.dist-info/RECORD
