Metadata-Version: 2.1
Name: pyTelegramBotCAPTCHA
Version: 1.1.4
Summary: An easy to use CAPTCHA solution for pyTelegramBotAPI.
Home-page: https://github.com/SwissCorePy/pyTelegramBotCAPTCHA
Download-URL: https://github.com/SwissCorePy/pyTelegramBotCAPTCHA/archive/refs/heads/main.zip
Author: SwissCorePy
Author-email: swisscore.py@gmail.com
License: gpl-3.0
Keywords: Telegram,Captcha,pyTelegramBotAPI
Platform: UNKNOWN
Classifier: Development Status :: 5 - Production/Stable
Classifier: Environment :: Console
Classifier: License :: OSI Approved :: GNU General Public License v3 (GPLv3)
Classifier: Programming Language :: Python :: 3
License-File: LICENSE
Requires-Dist: pyTelegramBotAPI (>=3.8.1)
Requires-Dist: captcha
Requires-Dist: Pillow
Provides-Extra: json
Requires-Dist: ujson ; extra == 'json'
